{
    "swagger": "2.0",
    "info": {
        "description": "Hire_Jobs is a platform to find your dream job.",
        "title": "Hireo Jobs API",
        "contact": {
            "name": "API Support"
        },
        "version": "1.0"
    },
    "paths": {
        "/employer/all-job-postings": {
            "get": {
                "security": [
                    {
                        "BearerTokenAuth": []
                    }
                ],
                "description": "Retrieve all job openings for the authenticated employer",
                "consumes": [
                    "application/json"
                ],
                "produces": [
                    "application/json"
                ],
                "tags": [
                    "Job Management"
                ],
                "summary": "Get all jobs",
                "parameters": [
                    {
                        "type": "string",
                        "description": "Bearer token",
                        "name": "Authorization",
                        "in": "header",
                        "required": true
                    }
                ],
                "responses": {
                    "200": {
                        "description": "Jobs retrieved successfully",
                        "schema": {
                            "$ref": "#/definitions/response.Response"
                        }
                    },
                    "400": {
                        "description": "Invalid employer ID type",
                        "schema": {
                            "$ref": "#/definitions/response.Response"
                        }
                    },
                    "401": {
                        "description": "Unauthorized",
                        "schema": {
                            "$ref": "#/definitions/response.Response"
                        }
                    },
                    "500": {
                        "description": "Failed to fetch jobs",
                        "schema": {
                            "$ref": "#/definitions/response.Response"
                        }
                    }
                }
            }
        },
        "/employer/chats": {
            "post": {
                "security": [
                    {
                        "ApiKeyAuth": []
                    }
                ],
                "description": "Retrieves chat details based on the provided request",
                "consumes": [
                    "application/json"
                ],
                "produces": [
                    "application/json"
                ],
                "tags": [
                    "Chat"
                ],
                "summary": "Retrieve chat details",
                "parameters": [
                    {
                        "description": "Chat request details",
                        "name": "body",
                        "in": "body",
                        "required": true,
                        "schema": {
                            "$ref": "#/definitions/models.ChatRequest"
                        }
                    }
                ],
                "responses": {
                    "200": {
                        "description": "Successfully retrieved chat details",
                        "schema": {
                            "$ref": "#/definitions/response.Response"
                        }
                    },
                    "400": {
                        "description": "Details not in correct format\" or \"User ID not found in JWT claims\" or \"Failed to get chat details",
                        "schema": {
                            "$ref": "#/definitions/response.Response"
                        }
                    }
                }
            }
        },
        "/employer/company": {
            "get": {
                "security": [
                    {
                        "BearerTokenAuth": []
                    }
                ],
                "description": "Retrieve details of the company deails with the authenticated employer",
                "consumes": [
                    "application/json"
                ],
                "produces": [
                    "application/json"
                ],
                "tags": [
                    "Employers"
                ],
                "summary": "Fetch company details",
                "parameters": [
                    {
                        "type": "string",
                        "description": "Bearer token",
                        "name": "Authorization",
                        "in": "header",
                        "required": true
                    }
                ],
                "responses": {
                    "200": {
                        "description": "Company details retrieved successfully",
                        "schema": {
                            "$ref": "#/definitions/response.Response"
                        }
                    },
                    "400": {
                        "description": "Invalid employer ID type",
                        "schema": {
                            "$ref": "#/definitions/response.Response"
                        }
                    },
                    "401": {
                        "description": "Unauthorized",
                        "schema": {
                            "$ref": "#/definitions/response.Response"
                        }
                    },
                    "500": {
                        "description": "Failed to fetch company details",
                        "schema": {
                            "$ref": "#/definitions/response.Response"
                        }
                    }
                }
            },
            "put": {
                "security": [
                    {
                        "BearerTokenAuth": []
                    }
                ],
                "description": "Update details of the company associated with the authenticated employer",
                "consumes": [
                    "application/json"
                ],
                "produces": [
                    "application/json"
                ],
                "tags": [
                    "Employers"
                ],
                "summary": "Update company details",
                "parameters": [
                    {
                        "type": "string",
                        "description": "Bearer token",
                        "name": "Authorization",
                        "in": "header",
                        "required": true
                    },
                    {
                        "description": "Employer details to update",
                        "name": "employerDetails",
                        "in": "body",
                        "required": true,
                        "schema": {
                            "$ref": "#/definitions/models.EmployerDetails"
                        }
                    }
                ],
                "responses": {
                    "200": {
                        "description": "Company updated successfully",
                        "schema": {
                            "$ref": "#/definitions/response.Response"
                        }
                    },
                    "400": {
                        "description": "Invalid employer ID type",
                        "schema": {
                            "$ref": "#/definitions/response.Response"
                        }
                    },
                    "401": {
                        "description": "Unauthorized",
                        "schema": {
                            "$ref": "#/definitions/response.Response"
                        }
                    },
                    "500": {
                        "description": "Failed to update company",
                        "schema": {
                            "$ref": "#/definitions/response.Response"
                        }
                    }
                }
            }
        },
        "/employer/get-applicants": {
            "get": {
                "description": "Retrieve the list of applicants for the jobs posted by the employer",
                "produces": [
                    "application/json"
                ],
                "tags": [
                    "Employers"
                ],
                "summary": "Get applicants for a job",
                "parameters": [
                    {
                        "type": "string",
                        "description": "Employer ID",
                        "name": "id",
                        "in": "header",
                        "required": true
                    }
                ],
                "responses": {
                    "200": {
                        "description": "Applicants retrieved successfully",
                        "schema": {
                            "$ref": "#/definitions/response.Response"
                        }
                    },
                    "400": {
                        "description": "Invalid employer ID type",
                        "schema": {
                            "$ref": "#/definitions/response.Response"
                        }
                    },
                    "500": {
                        "description": "Failed to fetch applicants",
                        "schema": {
                            "$ref": "#/definitions/response.Response"
                        }
                    }
                }
            }
        },
        "/employer/interviews": {
            "get": {
                "description": "Get interviews for a specific job by an employer",
                "consumes": [
                    "application/json"
                ],
                "produces": [
                    "application/json"
                ],
                "tags": [
                    "Employers"
                ],
                "summary": "Get interviews",
                "parameters": [
                    {
                        "type": "string",
                        "description": "User ID",
                        "name": "id",
                        "in": "header",
                        "required": true
                    },
                    {
                        "type": "string",
                        "description": "Job ID",
                        "name": "job_id",
                        "in": "query",
                        "required": true
                    }
                ],
                "responses": {
                    "200": {
                        "description": "Interview details fetched successfully",
                        "schema": {
                            "$ref": "#/definitions/response.Response"
                        }
                    },
                    "400": {
                        "description": "Invalid or missing user ID\" or \"Invalid job ID",
                        "schema": {
                            "$ref": "#/definitions/response.Response"
                        }
                    },
                    "500": {
                        "description": "Failed to fetch interview details",
                        "schema": {
                            "$ref": "#/definitions/response.Response"
                        }
                    }
                }
            }
        },
        "/employer/job-post": {
            "post": {
                "security": [
                    {
                        "BearerTokenAuth": []
                    }
                ],
                "description": "Create a new job opening for the authenticated employer",
                "consumes": [
                    "application/json"
                ],
                "produces": [
                    "application/json"
                ],
                "tags": [
                    "Job Management"
                ],
                "summary": "Post a job opening",
                "parameters": [
                    {
                        "type": "string",
                        "description": "Bearer token",
                        "name": "Authorization",
                        "in": "header",
                        "required": true
                    },
                    {
                        "type": "integer",
                        "description": "Employer ID",
                        "name": "employerID",
                        "in": "header",
                        "required": true
                    },
                    {
                        "description": "Job opening details",
                        "name": "jobOpening",
                        "in": "body",
                        "required": true,
                        "schema": {
                            "$ref": "#/definitions/models.JobOpening"
                        }
                    }
                ],
                "responses": {
                    "201": {
                        "description": "Job opening created successfully",
                        "schema": {
                            "$ref": "#/definitions/response.Response"
                        }
                    },
                    "400": {
                        "description": "Invalid employer ID type",
                        "schema": {
                            "$ref": "#/definitions/response.Response"
                        }
                    },
                    "401": {
                        "description": "Unauthorized",
                        "schema": {
                            "$ref": "#/definitions/response.Response"
                        }
                    },
                    "500": {
                        "description": "Failed to create job opening",
                        "schema": {
                            "$ref": "#/definitions/response.Response"
                        }
                    }
                }
            }
        },
        "/employer/job-postings": {
            "get": {
                "security": [
                    {
                        "BearerTokenAuth": []
                    }
                ],
                "description": "Retrieve a specific job opening for the authenticated employer",
                "consumes": [
                    "application/json"
                ],
                "produces": [
                    "application/json"
                ],
                "tags": [
                    "Job Management"
                ],
                "summary": "Get a job",
                "parameters": [
                    {
                        "type": "string",
                        "description": "Bearer token",
                        "name": "Authorization",
                        "in": "header",
                        "required": true
                    },
                    {
                        "type": "integer",
                        "description": "Job ID",
                        "name": "id",
                        "in": "query",
                        "required": true
                    }
                ],
                "responses": {
                    "200": {
                        "description": "Jobs retrieved successfully",
                        "schema": {
                            "$ref": "#/definitions/response.Response"
                        }
                    },
                    "400": {
                        "description": "Invalid job ID",
                        "schema": {
                            "$ref": "#/definitions/response.Response"
                        }
                    },
                    "401": {
                        "description": "Unauthorized",
                        "schema": {
                            "$ref": "#/definitions/response.Response"
                        }
                    },
                    "500": {
                        "description": "Failed to fetch jobs",
                        "schema": {
                            "$ref": "#/definitions/response.Response"
                        }
                    }
                }
            },
            "put": {
                "security": [
                    {
                        "BearerTokenAuth": []
                    }
                ],
                "description": "Update a specific job opening for the authenticated employer",
                "consumes": [
                    "application/json"
                ],
                "produces": [
                    "application/json"
                ],
                "tags": [
                    "Job Management"
                ],
                "summary": "Update a job",
                "parameters": [
                    {
                        "type": "string",
                        "description": "Bearer token",
                        "name": "Authorization",
                        "in": "header",
                        "required": true
                    },
                    {
                        "type": "integer",
                        "description": "Job ID",
                        "name": "id",
                        "in": "query",
                        "required": true
                    },
                    {
                        "description": "Job details",
                        "name": "job",
                        "in": "body",
                        "required": true,
                        "schema": {
                            "$ref": "#/definitions/models.JobOpening"
                        }
                    }
                ],
                "responses": {
                    "200": {
                        "description": "Job updated successfully",
                        "schema": {
                            "$ref": "#/definitions/response.Response"
                        }
                    },
                    "400": {
                        "description": "Details not in correct format",
                        "schema": {
                            "$ref": "#/definitions/response.Response"
                        }
                    },
                    "401": {
                        "description": "Unauthorized",
                        "schema": {
                            "$ref": "#/definitions/response.Response"
                        }
                    },
                    "500": {
                        "description": "Failed to update job",
                        "schema": {
                            "$ref": "#/definitions/response.Response"
                        }
                    }
                }
            },
            "delete": {
                "security": [
                    {
                        "BearerTokenAuth": []
                    }
                ],
                "description": "Delete a specific job opening for the authenticated employer",
                "consumes": [
                    "application/json"
                ],
                "produces": [
                    "application/json"
                ],
                "tags": [
                    "Job Management"
                ],
                "summary": "Delete a job",
                "parameters": [
                    {
                        "type": "string",
                        "description": "Bearer token",
                        "name": "Authorization",
                        "in": "header",
                        "required": true
                    },
                    {
                        "type": "integer",
                        "description": "Job ID",
                        "name": "id",
                        "in": "query",
                        "required": true
                    }
                ],
                "responses": {
                    "200": {
                        "description": "Job Deleted successfully",
                        "schema": {
                            "$ref": "#/definitions/response.Response"
                        }
                    },
                    "400": {
                        "description": "Invalid job ID",
                        "schema": {
                            "$ref": "#/definitions/response.Response"
                        }
                    },
                    "401": {
                        "description": "Unauthorized",
                        "schema": {
                            "$ref": "#/definitions/response.Response"
                        }
                    },
                    "500": {
                        "description": "Failed to delete job",
                        "schema": {
                            "$ref": "#/definitions/response.Response"
                        }
                    }
                }
            }
        },
        "/employer/login": {
            "post": {
                "description": "Process the employer login request",
                "consumes": [
                    "application/json"
                ],
                "produces": [
                    "application/json"
                ],
                "tags": [
                    "Employers Authentication"
                ],
                "summary": "Login for employer",
                "parameters": [
                    {
                        "description": "Employer Login details",
                        "name": "employer",
                        "in": "body",
                        "required": true,
                        "schema": {
                            "$ref": "#/definitions/models.EmployerLogin"
                        }
                    }
                ],
                "responses": {
                    "200": {
                        "description": "Employer authenticated successfully",
                        "schema": {
                            "$ref": "#/definitions/response.Response"
                        }
                    },
                    "400": {
                        "description": "Details not in correct format",
                        "schema": {
                            "$ref": "#/definitions/response.Response"
                        }
                    },
                    "500": {
                        "description": "Cannot authenticate employer",
                        "schema": {
                            "$ref": "#/definitions/response.Response"
                        }
                    }
                }
            }
        },
        "/employer/schedule-interview": {
            "post": {
                "description": "Schedule an interview for a jobseeker by an employer",
                "consumes": [
                    "application/json"
                ],
                "produces": [
                    "application/json"
                ],
                "tags": [
                    "Employers"
                ],
                "summary": "Schedule an interview",
                "parameters": [
                    {
                        "type": "string",
                        "description": "User ID",
                        "name": "id",
                        "in": "header",
                        "required": true
                    },
                    {
                        "type": "string",
                        "description": "Job ID",
                        "name": "job_id",
                        "in": "query",
                        "required": true
                    },
                    {
                        "type": "string",
                        "description": "Jobseeker ID",
                        "name": "jobseeker_id",
                        "in": "query",
                        "required": true
                    },
                    {
                        "type": "string",
                        "format": "YYYY-MM-DD",
                        "description": "Interview Date",
                        "name": "interview_date",
                        "in": "query",
                        "required": true
                    },
                    {
                        "type": "string",
                        "format": "HH:MM",
                        "description": "Interview Time",
                        "name": "interview_time",
                        "in": "query",
                        "required": true
                    },
                    {
                        "enum": [
                            "ONLINE",
                            "OFFLINE"
                        ],
                        "type": "string",
                        "description": "Interview Type",
                        "name": "interview_type",
                        "in": "query",
                        "required": true
                    },
                    {
                        "type": "string",
                        "description": "Interview Link",
                        "name": "link",
                        "in": "query"
                    }
                ],
                "responses": {
                    "200": {
                        "description": "Interview scheduled successfully",
                        "schema": {
                            "$ref": "#/definitions/response.Response"
                        }
                    },
                    "400": {
                        "description": "Invalid or missing user ID\" or \"Invalid job ID\" or \"Invalid jobseeker ID\" or \"Invalid interview date\" or \"Invalid interview time\" or \"Invalid interview type",
                        "schema": {
                            "$ref": "#/definitions/response.Response"
                        }
                    },
                    "500": {
                        "description": "Failed to schedule interview",
                        "schema": {
                            "$ref": "#/definitions/response.Response"
                        }
                    }
                }
            }
        },
        "/employer/signup": {
            "post": {
                "description": "Process the employer signup request",
                "consumes": [
                    "application/json"
                ],
                "produces": [
                    "application/json"
                ],
                "tags": [
                    "Employers Authentication"
                ],
                "summary": "Sign up a new employer",
                "parameters": [
                    {
                        "description": "Employer SignUp details",
                        "name": "employer",
                        "in": "body",
                        "required": true,
                        "schema": {
                            "$ref": "#/definitions/models.EmployerSignUp"
                        }
                    }
                ],
                "responses": {
                    "200": {
                        "description": "Employer created successfully",
                        "schema": {
                            "$ref": "#/definitions/response.Response"
                        }
                    },
                    "400": {
                        "description": "Details not in correct format",
                        "schema": {
                            "$ref": "#/definitions/response.Response"
                        }
                    },
                    "500": {
                        "description": "Cannot create employer",
                        "schema": {
                            "$ref": "#/definitions/response.Response"
                        }
                    }
                }
            }
        },
        "/group/:groupID/chat": {
            "get": {
                "security": [
                    {
                        "ApiKeyAuth": []
                    }
                ],
                "description": "Processes WebSocket messages for group chat based on the provided group ID",
                "consumes": [
                    "application/json"
                ],
                "produces": [
                    "application/json"
                ],
                "tags": [
                    "Chat"
                ],
                "summary": "Process WebSocket group chat messages",
                "parameters": [
                    {
                        "type": "string",
                        "description": "Group ID",
                        "name": "groupID",
                        "in": "path",
                        "required": true
                    }
                ],
                "responses": {
                    "200": {
                        "description": "WebSocket connection established",
                        "schema": {
                            "type": "string"
                        }
                    },
                    "400": {
                        "description": "Missing Authorization header\" or \"Invalid token\" or \"Websocket Connection Issue\" or \"Error reading WebSocket message\" or \"Details not in correct format",
                        "schema": {
                            "$ref": "#/definitions/response.Response"
                        }
                    }
                }
            }
        },
        "/job-seeker/apply-job": {
            "post": {
                "description": "Submit a job application with a resume and cover letter",
                "consumes": [
                    "multipart/form-data"
                ],
                "produces": [
                    "application/json"
                ],
                "tags": [
                    "Job Seeker"
                ],
                "summary": "Apply for a job",
                "parameters": [
                    {
                        "type": "string",
                        "description": "Employer ID",
                        "name": "id",
                        "in": "header",
                        "required": true
                    },
                    {
                        "type": "string",
                        "description": "Job ID",
                        "name": "job_id",
                        "in": "formData",
                        "required": true
                    },
                    {
                        "type": "string",
                        "description": "Cover Letter",
                        "name": "cover_letter",
                        "in": "formData",
                        "required": true
                    },
                    {
                        "type": "file",
                        "description": "Resume File",
                        "name": "resume",
                        "in": "formData",
                        "required": true
                    }
                ],
                "responses": {
                    "200": {
                        "description": "Job applied successfully",
                        "schema": {
                            "$ref": "#/definitions/response.Response"
                        }
                    },
                    "400": {
                        "description": "Invalid employer ID type or error in getting resume file",
                        "schema": {
                            "$ref": "#/definitions/response.Response"
                        }
                    },
                    "500": {
                        "description": "Failed to save/read resume file or apply for job",
                        "schema": {
                            "$ref": "#/definitions/response.Response"
                        }
                    }
                }
            }
        },
        "/job-seeker/apply-saved-job": {
            "post": {
                "description": "Apply to a job that has been saved by the user",
                "consumes": [
                    "multipart/form-data"
                ],
                "produces": [
                    "application/json"
                ],
                "tags": [
                    "Job Seeker"
                ],
                "summary": "Apply to a saved job",
                "parameters": [
                    {
                        "type": "string",
                        "description": "User ID",
                        "name": "id",
                        "in": "header",
                        "required": true
                    },
                    {
                        "type": "string",
                        "description": "Job ID",
                        "name": "job_id",
                        "in": "formData",
                        "required": true
                    },
                    {
                        "type": "string",
                        "description": "Cover Letter",
                        "name": "cover_letter",
                        "in": "formData"
                    },
                    {
                        "type": "file",
                        "description": "Resume File",
                        "name": "resume",
                        "in": "formData",
                        "required": true
                    }
                ],
                "responses": {
                    "200": {
                        "description": "Job applied successfully",
                        "schema": {
                            "$ref": "#/definitions/response.Response"
                        }
                    },
                    "400": {
                        "description": "Invalid or missing user ID\" or \"Invalid job ID\" or \"Error in getting resume file",
                        "schema": {
                            "$ref": "#/definitions/response.Response"
                        }
                    },
                    "404": {
                        "description": "No such saved job found",
                        "schema": {
                            "$ref": "#/definitions/response.Response"
                        }
                    },
                    "500": {
                        "description": "Failed to check saved jobs\" or \"Failed to save resume file\" or \"Failed to read resume file\" or \"Failed to apply for job",
                        "schema": {
                            "$ref": "#/definitions/response.Response"
                        }
                    }
                }
            }
        },
        "/job-seeker/jobs": {
            "get": {
                "description": "Retrieve the details of a specific job using its ID",
                "consumes": [
                    "application/json"
                ],
                "produces": [
                    "application/json"
                ],
                "tags": [
                    "Job Seeker"
                ],
                "summary": "Get job details",
                "parameters": [
                    {
                        "type": "string",
                        "description": "Job ID",
                        "name": "id",
                        "in": "query",
                        "required": true
                    }
                ],
                "responses": {
                    "200": {
                        "description": "Job details retrieved successfully",
                        "schema": {
                            "$ref": "#/definitions/response.Response"
                        }
                    },
                    "400": {
                        "description": "Invalid job ID",
                        "schema": {
                            "$ref": "#/definitions/response.Response"
                        }
                    },
                    "500": {
                        "description": "Failed to fetch job details",
                        "schema": {
                            "$ref": "#/definitions/response.Response"
                        }
                    }
                }
            }
        },
        "/job-seeker/save-jobs": {
            "post": {
                "description": "Save a job to the user's list of saved jobs",
                "produces": [
                    "application/json"
                ],
                "tags": [
                    "Job Seeker"
                ],
                "summary": "Save a job",
                "parameters": [
                    {
                        "type": "string",
                        "description": "Job ID",
                        "name": "job_id",
                        "in": "query",
                        "required": true
                    },
                    {
                        "type": "string",
                        "description": "User ID",
                        "name": "id",
                        "in": "header",
                        "required": true
                    }
                ],
                "responses": {
                    "200": {
                        "description": "Job saved successfully",
                        "schema": {
                            "$ref": "#/definitions/response.Response"
                        }
                    },
                    "400": {
                        "description": "Invalid or missing job ID\" or \"User ID not found\" or \"Invalid user ID type",
                        "schema": {
                            "$ref": "#/definitions/response.Response"
                        }
                    },
                    "500": {
                        "description": "Failed to save job",
                        "schema": {
                            "$ref": "#/definitions/response.Response"
                        }
                    }
                }
            }
        },
        "/job-seeker/saved-jobs": {
            "get": {
                "description": "Retrieve a job that has been saved by the user",
                "produces": [
                    "application/json"
                ],
                "tags": [
                    "Job Seeker"
                ],
                "summary": "Get a saved job",
                "parameters": [
                    {
                        "type": "string",
                        "description": "User ID",
                        "name": "id",
                        "in": "header",
                        "required": true
                    }
                ],
                "responses": {
                    "200": {
                        "description": "Job fetched successfully",
                        "schema": {
                            "$ref": "#/definitions/response.Response"
                        }
                    },
                    "400": {
                        "description": "User ID not found\" or \"Invalid user ID type",
                        "schema": {
                            "$ref": "#/definitions/response.Response"
                        }
                    },
                    "500": {
                        "description": "Failed to get job",
                        "schema": {
                            "$ref": "#/definitions/response.Response"
                        }
                    }
                }
            },
            "delete": {
                "description": "Delete a job from the user's list of saved jobs",
                "produces": [
                    "application/json"
                ],
                "tags": [
                    "Job Seeker"
                ],
                "summary": "Delete a saved job",
                "parameters": [
                    {
                        "type": "string",
                        "description": "Job ID",
                        "name": "job_id",
                        "in": "query",
                        "required": true
                    },
                    {
                        "type": "string",
                        "description": "User ID",
                        "name": "id",
                        "in": "header",
                        "required": true
                    }
                ],
                "responses": {
                    "200": {
                        "description": "Job deleted successfully",
                        "schema": {
                            "$ref": "#/definitions/response.Response"
                        }
                    },
                    "400": {
                        "description": "Invalid job ID format\" or \"Invalid or missing user ID\" or \"Invalid user ID type",
                        "schema": {
                            "$ref": "#/definitions/response.Response"
                        }
                    },
                    "500": {
                        "description": "Failed to delete job",
                        "schema": {
                            "$ref": "#/definitions/response.Response"
                        }
                    }
                }
            }
        },
        "/job-seeker/view-jobs": {
            "get": {
                "description": "Retrieve all job openings based on a keyword search for job seekers",
                "consumes": [
                    "application/json"
                ],
                "produces": [
                    "application/json"
                ],
                "tags": [
                    "Job Seeker"
                ],
                "summary": "View all jobs",
                "parameters": [
                    {
                        "type": "string",
                        "description": "Search keyword",
                        "name": "Keyword",
                        "in": "query",
                        "required": true
                    }
                ],
                "responses": {
                    "200": {
                        "description": "Jobs retrieved successfully",
                        "schema": {
                            "$ref": "#/definitions/response.Response"
                        }
                    },
                    "400": {
                        "description": "Keyword parameter is required",
                        "schema": {
                            "$ref": "#/definitions/response.Response"
                        }
                    },
                    "500": {
                        "description": "Failed to fetch jobs",
                        "schema": {
                            "$ref": "#/definitions/response.Response"
                        }
                    }
                }
            }
        },
        "/jobseeker/login": {
            "post": {
                "description": "Authenticate job seeker",
                "consumes": [
                    "application/json"
                ],
                "produces": [
                    "application/json"
                ],
                "tags": [
                    "Job Seekers Authentication"
                ],
                "summary": "Job seeker login",
                "parameters": [
                    {
                        "description": "Job seeker credentials",
                        "name": "request",
                        "in": "body",
                        "required": true,
                        "schema": {
                            "$ref": "#/definitions/models.JobSeekerLogin"
                        }
                    }
                ],
                "responses": {
                    "200": {
                        "description": "Job seeker authenticated successfully",
                        "schema": {
                            "$ref": "#/definitions/response.Response"
                        }
                    },
                    "400": {
                        "description": "Details not in correct format",
                        "schema": {
                            "$ref": "#/definitions/response.Response"
                        }
                    },
                    "500": {
                        "description": "Cannot authenticate job seeker",
                        "schema": {
                            "$ref": "#/definitions/response.Response"
                        }
                    }
                }
            }
        },
        "/jobseeker/signup": {
            "post": {
                "description": "Create a new job seeker account",
                "consumes": [
                    "application/json"
                ],
                "produces": [
                    "application/json"
                ],
                "tags": [
                    "Job Seekers Authentication"
                ],
                "summary": "Job seeker sign up",
                "parameters": [
                    {
                        "description": "Job seeker details",
                        "name": "request",
                        "in": "body",
                        "required": true,
                        "schema": {
                            "$ref": "#/definitions/models.JobSeekerSignUp"
                        }
                    }
                ],
                "responses": {
                    "200": {
                        "description": "Job seeker created successfully",
                        "schema": {
                            "$ref": "#/definitions/response.Response"
                        }
                    },
                    "400": {
                        "description": "Details not in correct format",
                        "schema": {
                            "$ref": "#/definitions/response.Response"
                        }
                    },
                    "500": {
                        "description": "Cannot create job seeker",
                        "schema": {
                            "$ref": "#/definitions/response.Response"
                        }
                    }
                }
            }
        }
    },
    "definitions": {
        "models.ChatRequest": {
            "type": "object",
            "required": [
                "friendID",
                "limit",
                "offset"
            ],
            "properties": {
                "friendID": {
                    "type": "string"
                },
                "limit": {
                    "type": "string"
                },
                "offset": {
                    "type": "string"
                }
            }
        },
        "models.EmployerDetails": {
            "type": "object",
            "properties": {
                "about_company": {
                    "type": "string"
                },
                "company_name": {
                    "type": "string"
                },
                "company_size": {
                    "type": "integer"
                },
                "contact_email": {
                    "type": "string"
                },
                "contact_phone_number": {
                    "type": "integer"
                },
                "headquarters_address": {
                    "type": "string"
                },
                "industry": {
                    "type": "string"
                },
                "password": {
                    "type": "string"
                },
                "website": {
                    "type": "string"
                }
            }
        },
        "models.EmployerLogin": {
            "type": "object",
            "required": [
                "email",
                "password"
            ],
            "properties": {
                "email": {
                    "type": "string"
                },
                "password": {
                    "type": "string",
                    "maxLength": 20,
                    "minLength": 6
                }
            }
        },
        "models.EmployerSignUp": {
            "type": "object",
            "properties": {
                "about_company": {
                    "type": "string"
                },
                "company_name": {
                    "type": "string"
                },
                "company_size": {
                    "type": "integer"
                },
                "contact_email": {
                    "type": "string"
                },
                "contact_phone_number": {
                    "type": "integer"
                },
                "headquarters_address": {
                    "type": "string"
                },
                "industry": {
                    "type": "string"
                },
                "password": {
                    "type": "string"
                },
                "website": {
                    "type": "string"
                }
            }
        },
        "models.JobOpening": {
            "type": "object",
            "properties": {
                "application_deadline": {
                    "type": "string"
                },
                "description": {
                    "type": "string"
                },
                "education_level": {
                    "type": "string"
                },
                "employment_type": {
                    "type": "string"
                },
                "experience_level": {
                    "type": "string"
                },
                "id": {
                    "type": "integer"
                },
                "location": {
                    "type": "string"
                },
                "requirements": {
                    "type": "string"
                },
                "salary": {
                    "type": "string"
                },
                "skills_required": {
                    "type": "string"
                },
                "title": {
                    "type": "string"
                }
            }
        },
        "models.JobSeekerLogin": {
            "type": "object",
            "required": [
                "email",
                "password"
            ],
            "properties": {
                "email": {
                    "type": "string"
                },
                "password": {
                    "type": "string",
                    "maxLength": 20,
                    "minLength": 6
                }
            }
        },
        "models.JobSeekerSignUp": {
            "type": "object",
            "required": [
                "email",
                "password"
            ],
            "properties": {
                "address": {
                    "type": "string"
                },
                "bio": {
                    "type": "string"
                },
                "date_of_birth": {
                    "type": "string"
                },
                "email": {
                    "type": "string"
                },
                "first_name": {
                    "type": "string"
                },
                "gender": {
                    "type": "string"
                },
                "last_name": {
                    "type": "string"
                },
                "password": {
                    "type": "string",
                    "maxLength": 20,
                    "minLength": 6
                },
                "phone_number": {
                    "type": "string"
                }
            }
        },
        "response.Response": {
            "type": "object",
            "properties": {
                "data": {},
                "error": {},
                "message": {
                    "type": "string"
                },
                "status_code": {
                    "type": "integer"
                }
            }
        }
    },
    "securityDefinitions": {
        "BearerTokenAuth": {
            "type": "apiKey",
            "name": "Authorization",
            "in": "header"
        }
    }
}